firefly_reports/__init__.py
firefly_reports/__main__.py
firefly_reports/config.py
firefly_reports/email.py
firefly_reports/firefly.py
firefly_reports-0.5.1.dist-info/METADATA
firefly_reports-0.5.1.dist-info/WHEEL
firefly_reports-0.5.1.dist-info/entry_points.txt
firefly_reports-0.5.1.dist-info/licenses/LICENSE
firefly_reports-0.5.1.dist-info/RECORD
