Metadata-Version: 2.4
Name: firefly_reports
Version: 0.5.1
Dynamic: Summary
Project-URL: Documentation, https://github.com/cetyler/firefly_reports/wiki
Project-URL: Source, https://github.com/cetyler/firefly_reports/wiki
Author-email: Christopher Tyler <ChristopherTyler@engineer.com>
License-File: LICENSE
Classifier: License :: OSI Approved :: MIT License
Requires-Python: >=3.12
Requires-Dist: beautifulsoup4>=4.13.4
Requires-Dist: click>=8.2.1
Requires-Dist: requests>=2.32.3
